LICENSE.txt
README.md
setup.cfg
setup.py
cmtpy/__init__.py
cmtpy/histogram_warping_ace.py
cmtpy.egg-info/PKG-INFO
cmtpy.egg-info/SOURCES.txt
cmtpy.egg-info/dependency_links.txt
cmtpy.egg-info/requires.txt
cmtpy.egg-info/top_level.txt