Metadata-Version: 2.1
Name: cmtpy
Version: 0.0.3
Summary: Tools for manipulating image contrast
Home-page: https://github.com/vik748/cmtpy
Author: vs
Author-email: vikrantshah+py@gmail.com
License: MIT
Keywords: contrast,histogram,enhancement
Platform: UNKNOWN
Classifier: Development Status :: 3 - Alpha
Classifier: Intended Audience :: Science/Research
Classifier: Topic :: Scientific/Engineering
Classifier: License :: OSI Approved :: MIT License
Classifier: Programming Language :: Python :: 3
Classifier: Programming Language :: Python :: 3.6
Classifier: Programming Language :: Python :: 3.7
Classifier: Programming Language :: Python :: 3.8
